pyerlc/__init__.py
pyerlc/client.py
pyerlc/exceptions.py
pyerlc/models.py
pyerlc/utils.py
pyerlc-1.1.0.dist-info/licenses/LICENSE
pyerlc-1.1.0.dist-info/METADATA
pyerlc-1.1.0.dist-info/WHEEL
pyerlc-1.1.0.dist-info/top_level.txt
pyerlc-1.1.0.dist-info/RECORD
