Metadata-Version: 2.4
Name: pyerlc
Version: 1.1.0
Summary: A Python wrapper for the ERLC PRC API
Author: epell Development
Author-email: epell Development <epell1@epelldevelopment.xyz>
License: MIT
Project-URL: Homepage, https://epelldevelopment.xyz
Project-URL: Repository, https://github.com/epell-development/erlc_py
Requires-Python: >=3.12
License-File: LICENSE
Requires-Dist: requests
Requires-Dist: colorama
Dynamic: author
Dynamic: license-file
Dynamic: requires-python
